bini_terminal_ascii_player-1.0.9.dist-info/licenses/LICENSE
terminal_media_player/__init__.py
terminal_media_player/cli.py
terminal_media_player/player.py
terminal_media_player/utils.py
bini_terminal_ascii_player-1.0.9.dist-info/METADATA
bini_terminal_ascii_player-1.0.9.dist-info/WHEEL
bini_terminal_ascii_player-1.0.9.dist-info/entry_points.txt
bini_terminal_ascii_player-1.0.9.dist-info/top_level.txt
bini_terminal_ascii_player-1.0.9.dist-info/RECORD
